venim/__init__.py
venim/cleaning.py
venim/config.py
venim/fits_cli.py
venim/image.py
venim/mask_functions.py
venim/pathmanager.py
venim/stats.py
venim/utils.py
venim/venim.py
venim/akatsuki/__init__.py
venim/akatsuki/ir2.py
venim-0.10.0.dist-info/AUTHORS.rst
venim-0.10.0.dist-info/LICENSE
venim-0.10.0.dist-info/METADATA
venim-0.10.0.dist-info/WHEEL
venim-0.10.0.dist-info/entry_points.txt
venim-0.10.0.dist-info/top_level.txt
venim-0.10.0.dist-info/RECORD
