Metadata-Version: 2.1
Name: venim
Version: 0.10.0
Summary: Python tools for Venus Image Analysis
Home-page: https://github.com/michaelaye/venim
Author: K.-Michael Aye
Author-email: kmichael.aye@gmail.com
License: MIT license
Keywords: venus images pds data
Platform: UNKNOWN
Classifier: Development Status :: 4 - Beta
Classifier: Intended Audience :: Developers
Classifier: Intended Audience :: Science/Research
Classifier: License :: OSI Approved :: MIT License
Classifier: Natural Language :: English
Classifier: Programming Language :: Python :: 3
Classifier: Programming Language :: Python :: 3.7
Classifier: Programming Language :: Python :: 3.8
Classifier: Programming Language :: Python :: 3 :: Only
Requires-Python: >=3.6, <4
Requires-Dist: numpy
Requires-Dist: pandas
Requires-Dist: matplotlib
Requires-Dist: planetarypy
Requires-Dist: urlpath
Requires-Dist: astropy
Requires-Dist: holoviews
Requires-Dist: circle-fit
Requires-Dist: fire
Requires-Dist: scikit-image
Requires-Dist: lxml
Requires-Dist: tqdm
Requires-Dist: ipywidgets
